{"type": "FeatureCollection", "features": [{"type": "Feature", "geometry": {"type": "Point", "coordinates": [80.1930125, 13.0877075]}, "properties": {"highway": "footway"}}, {"type": "Feature", "geometry": {"type": "Point", "coordinates": [80.1980622, 13.0890084]}, "properties": {"highway": "footway", "name": "Asiad colony park, walking path"}}, {"type": "Feature", "geometry": {"type": "Point", "coordinates": [80.198447, 13.084591]}, "properties": {"bicycle": "no", "foot": "designated", "highway": "footway", "horse": "no", "surface": "concrete"}}, {"type": "Feature", "geometry": {"type": "Point", "coordinates": [80.1984542, 13.0866381]}, "properties": {"bicycle": "no", "highway": "footway", "horse": "no", "surface": "concrete"}}, {"type": "Feature", "geometry": {"type": "Point", "coordinates": [80.1984527, 13.0888665]}, "properties": {"bicycle": "no", "highway": "footway", "horse": "no", "surface": "concrete"}}, {"type": "Feature", "geometry": {"type": "Point", "coordinates": [80.2082838, 13.0851366]}, "properties": {"foot": "yes", "footway": "sidewalk", "highway": "footway", "lit": "yes", "oneway": "yes", "surface": "concrete"}}, {"type": "Feature", "geometry": {"type": "Point", "coordinates": [80.1980293, 13.089013]}, "properties": {"highway": "footway", "name": "Asiad colony park, walking path"}}, {"type": "Feature", "geometry": {"type": "Point", "coordinates": [80.1987625, 13.0898381]}, "properties": {"highway": "footway"}}]}